fms_acceleration_peft/__init__.py
fms_acceleration_peft/autogptq_utils.py
fms_acceleration_peft/framework_plugin_autogptq.py
fms_acceleration_peft/framework_plugin_bnb.py
fms_acceleration_peft/fsdp_utils.py
fms_acceleration_peft/gptqmodel/__init__.py
fms_acceleration_peft/gptqmodel/models/__init__.py
fms_acceleration_peft/gptqmodel/models/_const.py
fms_acceleration_peft/gptqmodel/models/auto.py
fms_acceleration_peft/gptqmodel/models/base.py
fms_acceleration_peft/gptqmodel/models/dbrx.py
fms_acceleration_peft/gptqmodel/models/dbrx_converted.py
fms_acceleration_peft/gptqmodel/models/gemma.py
fms_acceleration_peft/gptqmodel/models/gpt_bigcode.py
fms_acceleration_peft/gptqmodel/models/gpt_neox.py
fms_acceleration_peft/gptqmodel/models/granite.py
fms_acceleration_peft/gptqmodel/models/llama.py
fms_acceleration_peft/gptqmodel/models/mistral.py
fms_acceleration_peft/gptqmodel/models/mixtral.py
fms_acceleration_peft/gptqmodel/nn_modules/__init__.py
fms_acceleration_peft/gptqmodel/nn_modules/qlinear/__init__.py
fms_acceleration_peft/gptqmodel/nn_modules/qlinear/qlinear_tritonv2.py
fms_acceleration_peft/gptqmodel/nn_modules/triton_utils/__init__.py
fms_acceleration_peft/gptqmodel/nn_modules/triton_utils/custom_autotune.py
fms_acceleration_peft/gptqmodel/nn_modules/triton_utils/dequant.py
fms_acceleration_peft/gptqmodel/nn_modules/triton_utils/kernels.py
fms_acceleration_peft/gptqmodel/nn_modules/triton_utils/mixin.py
fms_acceleration_peft/gptqmodel/quantization/__init__.py
fms_acceleration_peft/gptqmodel/quantization/config.py
fms_acceleration_peft/gptqmodel/quantization/gptq.py
fms_acceleration_peft/gptqmodel/quantization/quantizer.py
fms_acceleration_peft/gptqmodel/utils/__init__.py
fms_acceleration_peft/gptqmodel/utils/backend.py
fms_acceleration_peft/gptqmodel/utils/data.py
fms_acceleration_peft/gptqmodel/utils/importer.py
fms_acceleration_peft/gptqmodel/utils/model.py
fms_acceleration_peft/gptqmodel/utils/peft.py
fms_acceleration_peft-0.4.3.dist-info/METADATA
fms_acceleration_peft-0.4.3.dist-info/WHEEL
fms_acceleration_peft-0.4.3.dist-info/RECORD
