Metadata-Version: 2.4
Name: fms-acceleration-peft
Version: 0.4.3
Summary: FMS Acceleration for PeFT
Author-email: Fabian Lim <flim@sg.ibm.com>, Aaron Chew <aaron.chew1@ibm.com>
License: Apache-2.0
Keywords: acceleration,fms-hf-tuning,peft
Classifier: Development Status :: 4 - Beta
Classifier: License :: OSI Approved :: Apache Software License
Classifier: Programming Language :: Python :: 3
Classifier: Programming Language :: Python :: 3.9
Classifier: Programming Language :: Python :: 3.10
Classifier: Programming Language :: Python :: 3.11
Requires-Python: ~=3.9
Requires-Dist: accelerate>=0.29
Requires-Dist: bitsandbytes>=0.45.1
Requires-Dist: datasets>=2.20.0
Requires-Dist: threadpoolctl>=3.5.0
Provides-Extra: flash-attn
Requires-Dist: flash-attn; extra == 'flash-attn'
